{
  "article_id": "huggingface-blog--57819d9a",
  "author": "Hugging Face Blog",
  "content_chars": 7597,
  "content_sha256": "1bc6ba849fba9849df64fce971b3b5620cbe48300daa9117aa75c351d63237c9",
  "content_tokens": 1899,
  "fetched_at": "2026-04-21T06:55:24Z",
  "kind": "article",
  "published_at": "2025-10-23T00:00:00+00:00",
  "snippet": "Building the Open Agent Ecosystem Together: Introducing OpenEnv Hugging Face Models Datasets Spaces Buckets new Docs Enterprise Pricing Log In Sign Up Back to Articles Building the Open Agent Ecosystem Together: Introducing OpenEnv Published October 23, 2025 Update on GitHub…",
  "source_id": "huggingface-blog",
  "title": "Building the Open Agent Ecosystem Together: Introducing OpenEnv",
  "top_terms": [
    [
      "environments",
      20
    ],
    [
      "openenv",
      20
    ],
    [
      "environment",
      14
    ],
    [
      "follow",
      10
    ],
    [
      "tools",
      10
    ],
    [
      "agentic",
      9
    ],
    [
      "community",
      9
    ],
    [
      "face",
      8
    ],
    [
      "follow openenv",
      8
    ],
    [
      "hugging",
      8
    ],
    [
      "hugging face",
      8
    ],
    [
      "rl",
      8
    ],
    [
      "agent",
      7
    ],
    [
      "hub",
      7
    ],
    [
      "open",
      6
    ],
    [
      "the openenv",
      6
    ],
    [
      "agents",
      5
    ],
    [
      "next",
      5
    ],
    [
      "trl",
      5
    ],
    [
      "agentic development",
      4
    ]
  ],
  "url": "https://huggingface.co/blog/openenv",
  "url_canonical": "https://huggingface.co/blog/openenv",
  "via_source_id": null
}
