{
  "article_id": "huggingface-blog--00f36b75",
  "author": "Hugging Face Blog",
  "content_chars": 5594,
  "content_sha256": "dd00850c09b3827b8826437633d146a7a9f4ac50a68569e3ace372eccb6ef07b",
  "content_tokens": 1398,
  "fetched_at": "2026-04-29T07:06:29Z",
  "kind": "article",
  "published_at": "2025-08-04T19:51:50+00:00",
  "snippet": "Measuring Open-Source Llama Nemotron Models on DeepResearch Bench Hugging Face Models Datasets Spaces Buckets new Docs Enterprise Pricing Log In Sign Up Back to Articles Measuring Open-Source Llama Nemotron Models on DeepResearch Bench Enterprise + Article Published August 4…",
  "source_id": "huggingface-blog",
  "title": "Measuring Open-Source Llama Nemotron Models on DeepResearch Bench",
  "top_terms": [
    [
      "llama",
      11
    ],
    [
      "reasoning",
      10
    ],
    [
      "nvidia",
      9
    ],
    [
      "nemotron",
      8
    ],
    [
      "bench",
      7
    ],
    [
      "deepresearch",
      7
    ],
    [
      "deepresearch bench",
      7
    ],
    [
      "llama nemotron",
      7
    ],
    [
      "agent",
      6
    ],
    [
      "ai-q",
      6
    ],
    [
      "face",
      6
    ],
    [
      "hugging",
      6
    ],
    [
      "hugging face",
      6
    ],
    [
      "models",
      6
    ],
    [
      "agentic",
      5
    ],
    [
      "metrics",
      5
    ],
    [
      "model",
      5
    ],
    [
      "open-source",
      5
    ],
    [
      "search",
      5
    ],
    [
      "stack",
      5
    ]
  ],
  "url": "https://huggingface.co/blog/nvidia/ai-q-top-ranking-open-portable-deep-research-agent",
  "url_canonical": "https://huggingface.co/blog/nvidia/ai-q-top-ranking-open-portable-deep-research-agent",
  "via_source_id": null
}
