{
  "article_id": "one-useful-thing--68aef4e5",
  "author": "Ethan Mollick",
  "content_chars": 13677,
  "content_sha256": "732bc555553709595fa43a875f073e3062b598afcc13babe3811eb5bf5d5c112",
  "content_tokens": 3419,
  "fetched_at": "2026-04-13T19:19:50Z",
  "kind": "article",
  "published_at": "2025-11-12T02:46:43+00:00",
  "snippet": "Giving your AI a Job Interview - by Ethan Mollick One Useful Thing Subscribe Sign in Giving your AI a Job Interview As AI advice becomes more important, we are going to need to get better at assessing it Ethan Mollick Nov 12, 2025 398 32 25 Share Given how much energy, literal…",
  "source_id": "one-useful-thing",
  "title": "Giving your AI a Job Interview",
  "top_terms": [
    [
      "models",
      20
    ],
    [
      "model",
      15
    ],
    [
      "benchmarks",
      14
    ],
    [
      "better",
      12
    ],
    [
      "ais",
      11
    ],
    [
      "tasks",
      11
    ],
    [
      "tests",
      10
    ],
    [
      "different",
      9
    ],
    [
      "real",
      9
    ],
    [
      "benchmarking",
      7
    ],
    [
      "ability",
      6
    ],
    [
      "answers",
      6
    ],
    [
      "every",
      6
    ],
    [
      "example",
      6
    ],
    [
      "good",
      6
    ],
    [
      "interview",
      6
    ],
    [
      "job",
      6
    ],
    [
      "multiple",
      6
    ],
    [
      "test",
      6
    ],
    [
      "vibes",
      6
    ]
  ],
  "url": "https://www.oneusefulthing.org/p/giving-your-ai-a-job-interview",
  "url_canonical": "https://www.oneusefulthing.org/p/giving-your-ai-a-job-interview",
  "via_source_id": null
}
