{
  "article_id": "x-sama--48c64d96",
  "author": "Sam Altman",
  "content_chars": 133,
  "content_sha256": "c8a7f0bab45416c49e27faeceed9cf8f60ffb173de6aed139841d289d56b06b7",
  "content_tokens": 33,
  "fetched_at": "2026-04-30T07:09:24Z",
  "kind": "tweet",
  "published_at": "2026-04-30T00:55:24+00:00",
  "snippet": "we will have it at our SF HQ and pay for plane tickets & hotel for people who aren't local. we'll close the link tomorrow at 5:55 pm.",
  "source_id": "x-sama",
  "title": "we will have it at our SF HQ and pay for plane tickets & hotel for people who ar",
  "top_terms": [
    [
      "and pay",
      2
    ],
    [
      "and pay for",
      2
    ],
    [
      "at our sf",
      2
    ],
    [
      "for people",
      2
    ],
    [
      "for people who",
      2
    ],
    [
      "for plane",
      2
    ],
    [
      "for plane tickets",
      2
    ],
    [
      "hotel",
      2
    ],
    [
      "hotel for",
      2
    ],
    [
      "hotel for people",
      2
    ],
    [
      "hq",
      2
    ],
    [
      "hq and",
      2
    ],
    [
      "hq and pay",
      2
    ],
    [
      "our sf",
      2
    ],
    [
      "our sf hq",
      2
    ],
    [
      "pay",
      2
    ],
    [
      "pay for",
      2
    ],
    [
      "pay for plane",
      2
    ],
    [
      "people",
      2
    ],
    [
      "people who",
      2
    ]
  ],
  "url": "https://x.com/sama/status/2049653814463168638",
  "url_canonical": "https://x.com/sama/status/2049653814463168638",
  "via_source_id": null
}
