{
  "article_id": "x-simonw--da1be2a6",
  "author": "Simon Willison",
  "content_chars": 69,
  "content_sha256": "60a7a7dcf17a2281d2f2e895a9c281d882682c09645c7f1337f5bc4be54d1f18",
  "content_tokens": 17,
  "fetched_at": "2026-04-28T07:11:33Z",
  "kind": "tweet",
  "published_at": "2026-04-28T04:34:08+00:00",
  "snippet": "talkie was created by @status_effects and @DavidDuvenaud and @AlecRad",
  "source_id": "x-simonw",
  "title": "talkie was created by @status_effects and @DavidDuvenaud and @AlecRad",
  "top_terms": [
    [
      "alecrad",
      2
    ],
    [
      "and alecrad",
      2
    ],
    [
      "and davidduvenaud",
      2
    ],
    [
      "and davidduvenaud and",
      2
    ],
    [
      "by status",
      2
    ],
    [
      "by status effects",
      2
    ],
    [
      "created",
      2
    ],
    [
      "created by",
      2
    ],
    [
      "created by status",
      2
    ],
    [
      "davidduvenaud",
      2
    ],
    [
      "davidduvenaud and",
      2
    ],
    [
      "davidduvenaud and alecrad",
      2
    ],
    [
      "effects",
      2
    ],
    [
      "effects and",
      2
    ],
    [
      "effects and davidduvenaud",
      2
    ],
    [
      "status",
      2
    ],
    [
      "status effects",
      2
    ],
    [
      "status effects and",
      2
    ],
    [
      "talkie",
      2
    ],
    [
      "talkie was",
      2
    ]
  ],
  "url": "https://x.com/simonw/status/2048984084446376344",
  "url_canonical": "https://x.com/simonw/status/2048984084446376344",
  "via_source_id": null
}
