{
  "article_id": "x-demishassabis--ce2a83f5",
  "author": "Demis Hassabis",
  "content_chars": 195,
  "content_sha256": "a9cf82b320731a99840fe43a3b8c049e3bccc2bff252def878cc2353257467e6",
  "content_tokens": 48,
  "fetched_at": "2026-04-14T01:47:23Z",
  "kind": "tweet",
  "published_at": "2026-04-08T22:57:40+00:00",
  "snippet": "Lots of love for Gemma 4! Team just told me it’s already had 10M+ downloads since last week’s launch. Gemma models have now been downloaded 500M+ times! Excited to see what you all are creating 👀",
  "source_id": "x-demishassabis",
  "title": "Lots of love for Gemma 4! Team just told me it’s already had 10M+ downloads sinc",
  "top_terms": [
    [
      "gemma",
      3
    ],
    [
      "already",
      2
    ],
    [
      "already had",
      2
    ],
    [
      "downloads",
      2
    ],
    [
      "for gemma",
      2
    ],
    [
      "for gemma team",
      2
    ],
    [
      "gemma team",
      2
    ],
    [
      "gemma team just",
      2
    ],
    [
      "just told",
      2
    ],
    [
      "just told me",
      2
    ],
    [
      "lots",
      2
    ],
    [
      "lots of",
      2
    ],
    [
      "lots of love",
      2
    ],
    [
      "love",
      2
    ],
    [
      "love for",
      2
    ],
    [
      "love for gemma",
      2
    ],
    [
      "of love",
      2
    ],
    [
      "of love for",
      2
    ],
    [
      "team",
      2
    ],
    [
      "team just",
      2
    ]
  ],
  "url": "https://x.com/demishassabis/status/2042014040055276028",
  "url_canonical": "https://x.com/demishassabis/status/2042014040055276028",
  "via_source_id": null
}
